send_nsca3/__init__.py
send_nsca3/nagios.py
send_nsca3/nsca.py
send_nsca3-0.1.5.3.data/scripts/py_send_nsca3
send_nsca3-0.1.5.3.dist-info/LICENSE
send_nsca3-0.1.5.3.dist-info/METADATA
send_nsca3-0.1.5.3.dist-info/WHEEL
send_nsca3-0.1.5.3.dist-info/top_level.txt
send_nsca3-0.1.5.3.dist-info/RECORD
