Metadata-Version: 2.1
Name: send-nsca3
Version: 0.1.5.3
Summary: python3 compatible pure-python nsca sender
Home-page: https://github.com/gitmstoute/send_nsca3
Author: gitmstoute
Author-email: 
License: GNU Lesser General Public License v2 (LGPLv2)
Platform: UNKNOWN
Classifier: Programming Language :: Python
Classifier: Programming Language :: Python :: 3
Classifier: Operating System :: OS Independent
Classifier: License :: OSI Approved :: GNU Lesser General Public License v2 (LGPLv2)
Classifier: Topic :: System :: Monitoring
Classifier: Intended Audience :: Developers
Classifier: Development Status :: 4 - Beta
Provides: send_nsca3
Requires-Dist: pycrypto (>=2.0.0)
Requires-Dist: six
